{
  "name": "HWM_RULE_TMPLTS_TL",
  "object_type": "TABLE",
  "description": "Specifies formula and input and output variables for use with rule instances.",
  "schema": "FUSION",
  "owner": "HWM",
  "tablespace": "REFERENCE",
  "source_url": "https://docs.oracle.com/en/cloud/saas/human-resources/oedmh/hwmruletmpltstl-9388.html#hwmruletmpltstl-9388",
  "primary_keys": [
    {
      "name": "HWM_RULE_TMPLTS_TL_PK",
      "columns": "RULE_TMPLTS_ID, LANGUAGE"
    }
  ],
  "columns": [
    {
      "Name": "RULE_TMPLTS_ID",
      "Datatype": "NUMBER",
      "Length": "",
      "Precision": "18",
      "Not-null": "Yes",
      "Comments": "RULE_TMPLT_ID"
    },
    {
      "Name": "LANGUAGE",
      "Datatype": "VARCHAR2",
      "Length": "4",
      "Precision": "",
      "Not-null": "Yes",
      "Comments": "Indicates the code of the language into which the contents of the translatable columns are translated."
    },
    {
      "Name": "OBJECT_VERSION_NUMBER",
      "Datatype": "NUMBER",
      "Length": "",
      "Precision": "9",
      "Not-null": "Yes",
      "Comments": "Used to implement optimistic locking. This number is incremented every time that the row is updated. The number is compared at the start and end of a transaction to detect whether another session has updated the row since it was queried."
    },
    {
      "Name": "ENTERPRISE_ID",
      "Datatype": "NUMBER",
      "Length": "",
      "Precision": "18",
      "Not-null": "Yes",
      "Comments": "Standard Enterprise Identifier column for multi tenancy support"
    },
    {
      "Name": "SOURCE_LANG",
      "Datatype": "VARCHAR2",
      "Length": "4",
      "Precision": "",
      "Not-null": "Yes",
      "Comments": "Indicates the code of the language in which the contents of the translatable columns were originally created."
    },
    {
      "Name": "DESCRIPTION",
      "Datatype": "VARCHAR2",
      "Length": "300",
      "Precision": "",
      "Not-null": "",
      "Comments": "DESCRIPTION"
    },
    {
      "Name": "TRANSLATED_NAME",
      "Datatype": "VARCHAR2",
      "Length": "250",
      "Precision": "",
      "Not-null": "",
      "Comments": "Translated rule template name"
    },
    {
      "Name": "RT_EXPLANATION",
      "Datatype": "VARCHAR2",
      "Length": "2000",
      "Precision": "",
      "Not-null": "",
      "Comments": "RT_EXPLANATION"
    },
    {
      "Name": "CREATED_BY",
      "Datatype": "VARCHAR2",
      "Length": "64",
      "Precision": "",
      "Not-null": "Yes",
      "Comments": "Who column: indicates the user who created the row."
    },
    {
      "Name": "CREATION_DATE",
      "Datatype": "TIMESTAMP",
      "Length": "",
      "Precision": "",
      "Not-null": "Yes",
      "Comments": "Who column: indicates the date and time of the creation of the row."
    },
    {
      "Name": "LAST_UPDATED_BY",
      "Datatype": "VARCHAR2",
      "Length": "64",
      "Precision": "",
      "Not-null": "Yes",
      "Comments": "Who column: indicates the user who last updated the row."
    },
    {
      "Name": "LAST_UPDATE_DATE",
      "Datatype": "TIMESTAMP",
      "Length": "",
      "Precision": "",
      "Not-null": "Yes",
      "Comments": "Who column: indicates the date and time of the last update of the row."
    },
    {
      "Name": "LAST_UPDATE_LOGIN",
      "Datatype": "VARCHAR2",
      "Length": "32",
      "Precision": "",
      "Not-null": "",
      "Comments": "Who column: indicates the session login associated to the user who last updated the row."
    },
    {
      "Name": "SEED_DATA_SOURCE",
      "Datatype": "VARCHAR2",
      "Length": "512",
      "Precision": "",
      "Not-null": "",
      "Comments": "Source of seed data record. A value of 'BULK_SEED_DATA_SCRIPT' indicates that record was bulk loaded. Otherwise, specifies the name of the seed data file."
    },
    {
      "Name": "ORA_SEED_SET1",
      "Datatype": "VARCHAR2",
      "Length": "1",
      "Precision": "",
      "Not-null": "Yes",
      "Comments": "Oracle internal use only. Indicates the edition-based redefinition (EBR) context of the row for SET1. Context values are Y or N."
    },
    {
      "Name": "ORA_SEED_SET2",
      "Datatype": "VARCHAR2",
      "Length": "1",
      "Precision": "",
      "Not-null": "Yes",
      "Comments": "Oracle internal use only. Indicates the edition-based redefinition (EBR) context of the row for SET2. Context values are Y or N."
    }
  ],
  "indexes": [
    {
      "Index": "HWM_RULE_TMPLTS_TL_U1",
      "Uniqueness": "Unique",
      "Tablespace": "Default",
      "Columns": "RULE_TMPLTS_ID, LANGUAGE, ORA_SEED_SET1"
    },
    {
      "Index": "HWM_RULE_TMPLTS_TL_U11",
      "Uniqueness": "Unique",
      "Tablespace": "Default",
      "Columns": "RULE_TMPLTS_ID, LANGUAGE, ORA_SEED_SET2"
    }
  ],
  "_parsed_at": "2026-06-09T19:43:13"
}