{
  "name": "CMP_INSTRUCTIONS_B",
  "object_type": "TABLE",
  "description": "Stores setup instructions information.",
  "schema": "FUSION",
  "owner": "CMP",
  "tablespace": "FUSION_TS_TX_DATA",
  "source_url": "https://docs.oracle.com/en/cloud/saas/human-resources/oedmh/cmpinstructionsb-15422.html#cmpinstructionsb-15422",
  "primary_keys": [
    {
      "name": "CMP_INSTRUCTIONS_B_PK",
      "columns": "INSTRUCTION_ID"
    }
  ],
  "columns": [
    {
      "Name": "INSTRUCTION_ID",
      "Datatype": "NUMBER",
      "Length": "",
      "Precision": "18",
      "Not-null": "Yes",
      "Comments": "INSTRUCTION_ID"
    },
    {
      "Name": "BUSINESS_GROUP_ID",
      "Datatype": "NUMBER",
      "Length": "",
      "Precision": "18",
      "Not-null": "Yes",
      "Comments": "BUSINESS_GROUP_ID"
    },
    {
      "Name": "COMP_TYPE",
      "Datatype": "VARCHAR2",
      "Length": "30",
      "Precision": "",
      "Not-null": "",
      "Comments": "COMP_TYPE"
    },
    {
      "Name": "KEY_TYPE",
      "Datatype": "VARCHAR2",
      "Length": "30",
      "Precision": "",
      "Not-null": "",
      "Comments": "KEY_TYPE"
    },
    {
      "Name": "INSTRUCTION_KEY",
      "Datatype": "NUMBER",
      "Length": "",
      "Precision": "18",
      "Not-null": "",
      "Comments": "INSTRUCTION_KEY"
    },
    {
      "Name": "INSTRUCTION_TYPE",
      "Datatype": "VARCHAR2",
      "Length": "30",
      "Precision": "",
      "Not-null": "",
      "Comments": "INSTRUCTION_TYPE"
    },
    {
      "Name": "OBJECT_VERSION_NUMBER",
      "Datatype": "NUMBER",
      "Length": "",
      "Precision": "9",
      "Not-null": "Yes",
      "Comments": "Used to implement optimistic locking. This number is incremented every time that the row is updated. The number is compared at the start and end of a transaction to detect whether another session has updated the row since it was queried."
    },
    {
      "Name": "CREATED_BY",
      "Datatype": "VARCHAR2",
      "Length": "64",
      "Precision": "",
      "Not-null": "Yes",
      "Comments": "Who column: indicates the user who created the row."
    },
    {
      "Name": "CREATION_DATE",
      "Datatype": "TIMESTAMP",
      "Length": "",
      "Precision": "",
      "Not-null": "Yes",
      "Comments": "Who column: indicates the date and time of the creation of the row."
    },
    {
      "Name": "LAST_UPDATED_BY",
      "Datatype": "VARCHAR2",
      "Length": "64",
      "Precision": "",
      "Not-null": "Yes",
      "Comments": "Who column: indicates the user who last updated the row."
    },
    {
      "Name": "LAST_UPDATE_DATE",
      "Datatype": "TIMESTAMP",
      "Length": "",
      "Precision": "",
      "Not-null": "Yes",
      "Comments": "Who column: indicates the date and time of the last update of the row."
    },
    {
      "Name": "LAST_UPDATE_LOGIN",
      "Datatype": "VARCHAR2",
      "Length": "32",
      "Precision": "",
      "Not-null": "",
      "Comments": "Who column: indicates the session login associated to the user who last updated the row."
    }
  ],
  "indexes": [
    {
      "Index": "CMP_INSTRUCTIONS_B_N1",
      "Uniqueness": "Non Unique",
      "Tablespace": "Default",
      "Columns": "INSTRUCTION_KEY, KEY_TYPE"
    },
    {
      "Index": "CMP_INSTRUCTIONS_B_UK1",
      "Uniqueness": "Unique",
      "Tablespace": "Default",
      "Columns": "INSTRUCTION_ID"
    }
  ],
  "_parsed_at": "2026-06-10T07:28:56"
}