{
  "name": "CMP_CWB_APPROVAL_HISTORY",
  "object_type": "TABLE",
  "description": "This Table stores the Approval History for all the managers",
  "schema": "FUSION",
  "owner": "CMP",
  "tablespace": "FUSION_TS_TX_DATA",
  "source_url": "https://docs.oracle.com/en/cloud/saas/human-resources/oedmh/cmpcwbapprovalhistory-29766.html#cmpcwbapprovalhistory-29766",
  "primary_keys": [
    {
      "name": "CMP_CWB_APPROVAL_HISTORY_PK",
      "columns": "APPROVAL_HISTORY_ID"
    }
  ],
  "columns": [
    {
      "Name": "APPROVAL_HISTORY_ID",
      "Datatype": "NUMBER",
      "Length": "",
      "Precision": "18",
      "Not-null": "Yes",
      "Comments": "APPROVAL_HISTORY_ID",
      "Status": ""
    },
    {
      "Name": "BUSINESS_GROUP_ID",
      "Datatype": "NUMBER",
      "Length": "",
      "Precision": "18",
      "Not-null": "Yes",
      "Comments": "BUSINESS_GROUP_ID",
      "Status": ""
    },
    {
      "Name": "MGR_PERSON_EVENT_ID",
      "Datatype": "NUMBER",
      "Length": "",
      "Precision": "18",
      "Not-null": "",
      "Comments": "MGR_PERSON_EVENT_ID",
      "Status": ""
    },
    {
      "Name": "EMP_PERSON_EVENT_ID",
      "Datatype": "NUMBER",
      "Length": "",
      "Precision": "18",
      "Not-null": "Yes",
      "Comments": "EMP_PERSON_EVENT_ID",
      "Status": ""
    },
    {
      "Name": "MGR_ASSIGNMENT_ID",
      "Datatype": "NUMBER",
      "Length": "",
      "Precision": "18",
      "Not-null": "",
      "Comments": "MGR_ASSIGNMENT_ID",
      "Status": ""
    },
    {
      "Name": "ACTION_CODE",
      "Datatype": "VARCHAR2",
      "Length": "30",
      "Precision": "",
      "Not-null": "Yes",
      "Comments": "APPR_ACTION",
      "Status": ""
    },
    {
      "Name": "ACTION_DATE",
      "Datatype": "TIMESTAMP",
      "Length": "",
      "Precision": "",
      "Not-null": "Yes",
      "Comments": "ACTION_DATE",
      "Status": ""
    },
    {
      "Name": "COMMENTS",
      "Datatype": "CLOB",
      "Length": "",
      "Precision": "",
      "Not-null": "",
      "Comments": "COMMENTS",
      "Status": ""
    },
    {
      "Name": "OBJECT_VERSION_NUMBER",
      "Datatype": "NUMBER",
      "Length": "",
      "Precision": "9",
      "Not-null": "Yes",
      "Comments": "Used to implement optimistic locking. This number is incremented every time that the row is updated. The number is compared at the start and end of a transaction to detect whether another session has updated the row since it was queried.",
      "Status": "Active"
    },
    {
      "Name": "CREATED_BY",
      "Datatype": "VARCHAR2",
      "Length": "64",
      "Precision": "",
      "Not-null": "Yes",
      "Comments": "Who column: indicates the user who created the row.",
      "Status": "Active"
    },
    {
      "Name": "CREATION_DATE",
      "Datatype": "TIMESTAMP",
      "Length": "",
      "Precision": "",
      "Not-null": "Yes",
      "Comments": "Who column: indicates the date and time of the creation of the row.",
      "Status": "Active"
    },
    {
      "Name": "LAST_UPDATED_BY",
      "Datatype": "VARCHAR2",
      "Length": "64",
      "Precision": "",
      "Not-null": "Yes",
      "Comments": "Who column: indicates the user who last updated the row.",
      "Status": "Active"
    },
    {
      "Name": "LAST_UPDATE_DATE",
      "Datatype": "TIMESTAMP",
      "Length": "",
      "Precision": "",
      "Not-null": "Yes",
      "Comments": "Who column: indicates the date and time of the last update of the row.",
      "Status": "Active"
    },
    {
      "Name": "LAST_UPDATE_LOGIN",
      "Datatype": "VARCHAR2",
      "Length": "32",
      "Precision": "",
      "Not-null": "",
      "Comments": "Who column: indicates the session login associated to the user who last updated the row.",
      "Status": "Active"
    },
    {
      "Name": "POOL_ID",
      "Datatype": "NUMBER",
      "Length": "",
      "Precision": "18",
      "Not-null": "",
      "Comments": "POOL_ID",
      "Status": ""
    }
  ],
  "indexes": [
    {
      "Index": "CMP_CWB_APPROVAL_HISTORY_N1",
      "Uniqueness": "Non Unique",
      "Tablespace": "FUSION_TS_TX_DATA",
      "Columns": "EMP_PERSON_EVENT_ID, MGR_ASSIGNMENT_ID"
    },
    {
      "Index": "CMP_CWB_APPROVAL_HISTORY_PK",
      "Uniqueness": "Unique",
      "Tablespace": "FUSION_TS_TX_DATA",
      "Columns": "APPROVAL_HISTORY_ID"
    }
  ],
  "_parsed_at": "2026-06-10T08:15:16"
}