{
  "name": "WLF_LMC_OBJECTIVE_ATTEMPTS",
  "object_type": "TABLE",
  "description": "Attempts made on an objective within an Attempt on a content object",
  "schema": "FUSION",
  "owner": "WLF",
  "tablespace": "FUSION_TS_TX_DATA",
  "source_url": "https://docs.oracle.com/en/cloud/saas/human-resources/oedmh/wlflmcobjectiveattempts-18108.html#wlflmcobjectiveattempts-18108",
  "primary_keys": [
    {
      "name": "WLF_LMC_OBJECTIVE_ATTEMPTS_PK",
      "columns": "OBJECTIVE_ATTEMPT_ID"
    }
  ],
  "columns": [
    {
      "Name": "OBJECTIVE_ATTEMPT_ID",
      "Datatype": "NUMBER",
      "Length": "",
      "Precision": "18",
      "Not-null": "Yes",
      "Comments": "OBJECTIVE_ATTEMPT_ID"
    },
    {
      "Name": "ATTEMPT_ID",
      "Datatype": "NUMBER",
      "Length": "",
      "Precision": "18",
      "Not-null": "Yes",
      "Comments": "ATTEMPT_ID"
    },
    {
      "Name": "OBJECTIVE_ID",
      "Datatype": "NUMBER",
      "Length": "",
      "Precision": "18",
      "Not-null": "Yes",
      "Comments": "OBJECTIVE_ID"
    },
    {
      "Name": "RAW_STATUS",
      "Datatype": "VARCHAR2",
      "Length": "1",
      "Precision": "",
      "Not-null": "Yes",
      "Comments": "RAW_STATUS"
    },
    {
      "Name": "RAW_SCORE",
      "Datatype": "VARCHAR2",
      "Length": "80",
      "Precision": "",
      "Not-null": "Yes",
      "Comments": "RAW_SCORE"
    },
    {
      "Name": "SUCCESS_STATUS",
      "Datatype": "VARCHAR2",
      "Length": "1",
      "Precision": "",
      "Not-null": "",
      "Comments": "SUCCESS_STATUS"
    },
    {
      "Name": "COMPLETION_STATUS",
      "Datatype": "VARCHAR2",
      "Length": "1",
      "Precision": "",
      "Not-null": "",
      "Comments": "COMPLETION_STATUS"
    },
    {
      "Name": "SCALED_SCORE",
      "Datatype": "NUMBER",
      "Length": "",
      "Precision": "",
      "Not-null": "",
      "Comments": "SCALED_SCORE"
    },
    {
      "Name": "MIN_SCORE",
      "Datatype": "NUMBER",
      "Length": "",
      "Precision": "",
      "Not-null": "",
      "Comments": "MIN_SCORE"
    },
    {
      "Name": "MAX_SCORE",
      "Datatype": "NUMBER",
      "Length": "",
      "Precision": "",
      "Not-null": "",
      "Comments": "MAX_SCORE"
    },
    {
      "Name": "PROGRESS_MEASURE",
      "Datatype": "NUMBER",
      "Length": "",
      "Precision": "",
      "Not-null": "",
      "Comments": "PROGRESS_MEASURE"
    },
    {
      "Name": "DESCRIPTION",
      "Datatype": "VARCHAR2",
      "Length": "4000",
      "Precision": "",
      "Not-null": "",
      "Comments": "DESCRIPTION"
    },
    {
      "Name": "CREATED_BY",
      "Datatype": "VARCHAR2",
      "Length": "64",
      "Precision": "",
      "Not-null": "Yes",
      "Comments": "Who column: indicates the user who created the row."
    },
    {
      "Name": "CREATION_DATE",
      "Datatype": "TIMESTAMP",
      "Length": "",
      "Precision": "",
      "Not-null": "Yes",
      "Comments": "Who column: indicates the date and time of the creation of the row."
    },
    {
      "Name": "LAST_UPDATED_BY",
      "Datatype": "VARCHAR2",
      "Length": "64",
      "Precision": "",
      "Not-null": "Yes",
      "Comments": "Who column: indicates the user who last updated the row."
    },
    {
      "Name": "LAST_UPDATE_DATE",
      "Datatype": "TIMESTAMP",
      "Length": "",
      "Precision": "",
      "Not-null": "Yes",
      "Comments": "Who column: indicates the date and time of the last update of the row."
    },
    {
      "Name": "LAST_UPDATE_LOGIN",
      "Datatype": "VARCHAR2",
      "Length": "32",
      "Precision": "",
      "Not-null": "",
      "Comments": "Who column: indicates the session login associated to the user who last updated the row."
    },
    {
      "Name": "OBJECT_VERSION_NUMBER",
      "Datatype": "NUMBER",
      "Length": "",
      "Precision": "9",
      "Not-null": "Yes",
      "Comments": "Used to implement optimistic locking. This number is incremented every time that the row is updated. The number is compared at the start and end of a transaction to detect whether another session has updated the row since it was queried."
    },
    {
      "Name": "ENTERPRISE_ID",
      "Datatype": "NUMBER",
      "Length": "",
      "Precision": "18",
      "Not-null": "Yes",
      "Comments": "ENTERPRISE_ID"
    }
  ],
  "indexes": [
    {
      "Index": "WLF_LMC_OBJECTIVE_ATTEMPTS_N1",
      "Uniqueness": "Non Unique",
      "Tablespace": "Default",
      "Columns": "ATTEMPT_ID, OBJECTIVE_ID"
    },
    {
      "Index": "WLF_LMC_OBJECTIVE_ATTEMPTS_PK",
      "Uniqueness": "Unique",
      "Tablespace": "FUSION_TS_TX_DATA",
      "Columns": "OBJECTIVE_ATTEMPT_ID"
    }
  ],
  "_parsed_at": "2026-06-09T19:21:54"
}