{
  "name": "HRA_TMPL_DEFNS_B_R10",
  "object_type": "VIEW",
  "description": "",
  "schema": "FUSION",
  "owner": "HRA",
  "source_url": "https://docs.oracle.com/en/cloud/saas/human-resources/oedmh/hratmpldefnsbr10-8228.html#hratmpldefnsbr10-8228",
  "columns": [
    "TEMPLATE_DEFN_ID",
    "USE_CALC_RATINGS_FLAG",
    "BUSINESS_GROUP_ID",
    "SET_ID",
    "DOC_TYPE_ID",
    "PROCESS_FLOW_ID",
    "DATE_FROM",
    "DATE_TO",
    "STATUS_CODE",
    "CALCULATE_RATINGS_FLAG",
    "ROUNDING_RULE_CODE",
    "DECIMAL_PLACES",
    "MAPPING_METHOD_CODE",
    "SHOW_PARTICIPANT_NAMES",
    "SELECT_MGR_ALLOWED_FLAG",
    "STAR_RATING_ENABLED_FLAG",
    "SET_ROLE_MINIMUMS_FLAG",
    "TOTAL_MIN_PARTICIPANTS",
    "USE_WRK_CONNECTIONS_FLAG",
    "WRK_SEE_MGR_PCPN_FLAG",
    "PCPN_FEEDBACK_REQ_FLAG",
    "PCPN_DECLINE_OPTION_FLAG",
    "AUTO_POPULATE_MM_FLAG",
    "SEND_REQUEST_TO_MM_FLAG",
    "DEFAULT_MATRIX_PCPN_ROLE_ID",
    "ATTRIBUTE_CATEGORY",
    "ATTRIBUTE1",
    "ATTRIBUTE2",
    "ATTRIBUTE3",
    "ATTRIBUTE4",
    "ATTRIBUTE5",
    "ATTRIBUTE6",
    "ATTRIBUTE7",
    "ATTRIBUTE8",
    "ATTRIBUTE9",
    "ATTRIBUTE10",
    "ATTRIBUTE11",
    "ATTRIBUTE12",
    "ATTRIBUTE13",
    "ATTRIBUTE14",
    "ATTRIBUTE15",
    "ATTRIBUTE16",
    "ATTRIBUTE17",
    "ATTRIBUTE18",
    "ATTRIBUTE19",
    "ATTRIBUTE20",
    "ATTRIBUTE21",
    "ATTRIBUTE22",
    "ATTRIBUTE23",
    "ATTRIBUTE24",
    "ATTRIBUTE25",
    "ATTRIBUTE26",
    "ATTRIBUTE27",
    "ATTRIBUTE28",
    "ATTRIBUTE29",
    "ATTRIBUTE30",
    "ATTRIBUTE_NUMBER1",
    "ATTRIBUTE_NUMBER2",
    "ATTRIBUTE_NUMBER3",
    "ATTRIBUTE_NUMBER4",
    "ATTRIBUTE_NUMBER5",
    "ATTRIBUTE_NUMBER6",
    "ATTRIBUTE_NUMBER7",
    "ATTRIBUTE_NUMBER8",
    "ATTRIBUTE_NUMBER9",
    "ATTRIBUTE_NUMBER10",
    "ATTRIBUTE_NUMBER11",
    "ATTRIBUTE_NUMBER12",
    "ATTRIBUTE_NUMBER13",
    "ATTRIBUTE_NUMBER14",
    "ATTRIBUTE_NUMBER15",
    "ATTRIBUTE_NUMBER16",
    "ATTRIBUTE_NUMBER17",
    "ATTRIBUTE_NUMBER18",
    "ATTRIBUTE_NUMBER19",
    "ATTRIBUTE_NUMBER20",
    "ATTRIBUTE_DATE1",
    "ATTRIBUTE_DATE2",
    "ATTRIBUTE_DATE3",
    "ATTRIBUTE_DATE4",
    "ATTRIBUTE_DATE5",
    "ATTRIBUTE_DATE6",
    "ATTRIBUTE_DATE7",
    "ATTRIBUTE_DATE8",
    "ATTRIBUTE_DATE9",
    "ATTRIBUTE_DATE10",
    "ATTRIBUTE_DATE11",
    "ATTRIBUTE_DATE12",
    "ATTRIBUTE_DATE13",
    "ATTRIBUTE_DATE14",
    "ATTRIBUTE_DATE15",
    "OBJECT_VERSION_NUMBER",
    "CREATED_BY",
    "CREATION_DATE",
    "LAST_UPDATED_BY",
    "LAST_UPDATE_DATE",
    "LAST_UPDATE_LOGIN",
    "DIGITAL_SIGNATURE_FLAG",
    "MODULE_ID",
    "KUDOS_REGION_FLAG",
    "SHOW_WKR_CALC_RATING_FLAG",
    "SHOW_MGR_CALC_RATING_FLAG",
    "SHOW_MM_CALC_RATING_FLAG",
    "SHOW_PCPN_CALC_RATING_FLAG"
  ],
  "query": "SELECT HRA_TMPL_DEFNS_B.TEMPLATE_DEFN_ID TEMPLATE_DEFN_ID, HRA_TMPL_DEFNS_B.USE_CALC_RATINGS_FLAG USE_CALC_RATINGS_FLAG, HRA_TMPL_DEFNS_B.BUSINESS_GROUP_ID BUSINESS_GROUP_ID, HRA_TMPL_DEFNS_B.SET_ID SET_ID, HRA_TMPL_DEFNS_B.DOC_TYPE_ID DOC_TYPE_ID, HRA_TMPL_DEFNS_B.PROCESS_FLOW_ID PROCESS_FLOW_ID, HRA_TMPL_DEFNS_B.DATE_FROM DATE_FROM, HRA_TMPL_DEFNS_B.DATE_TO DATE_TO, HRA_TMPL_DEFNS_B.STATUS_CODE STATUS_CODE, HRA_TMPL_DEFNS_B.CALCULATE_RATINGS_FLAG CALCULATE_RATINGS_FLAG, CASE WHEN EXISTS (SELECT 1 FROM HRA_TMPL_SECTIONS WHERE HRA_TMPL_SECTIONS.TEMPLATE_DEFN_ID = HRA_TMPL_DEFNS_B.TEMPLATE_DEFN_ID AND HRA_TMPL_SECTIONS.BUSINESS_GROUP_ID = HRA_TMPL_DEFNS_B.BUSINESS_GROUP_ID AND SECTION_TYPE_CODE = 'OS') THEN (SELECT ROUNDING_RULE_CODE FROM HRA_TMPL_SECTIONS WHERE HRA_TMPL_SECTIONS.TEMPLATE_DEFN_ID = HRA_TMPL_DEFNS_B.TEMPLATE_DEFN_ID AND HRA_TMPL_SECTIONS.BUSINESS_GROUP_ID = HRA_TMPL_DEFNS_B.BUSINESS_GROUP_ID AND SECTION_TYPE_CODE = 'OS') WHEN EXISTS (SELECT 1 FROM HRA_TMPL_SECTIONS WHERE HRA_TMPL_SECTIONS.TEMPLATE_DEFN_ID = HRA_TMPL_DEFNS_B.TEMPLATE_DEFN_ID AND HRA_TMPL_SECTIONS.BUSINESS_GROUP_ID = HRA_TMPL_DEFNS_B.BUSINESS_GROUP_ID AND SECTION_TYPE_CODE = 'REG') THEN (SELECT ROUNDING_RULE_CODE FROM HRA_TMPL_SECTIONS WHERE HRA_TMPL_SECTIONS.TEMPLATE_DEFN_ID = HRA_TMPL_DEFNS_B.TEMPLATE_DEFN_ID AND HRA_TMPL_SECTIONS.BUSINESS_GROUP_ID = HRA_TMPL_DEFNS_B.BUSINESS_GROUP_ID AND SECTION_TYPE_CODE = 'REG') WHEN EXISTS (SELECT 1 FROM HRA_TMPL_SECTIONS WHERE HRA_TMPL_SECTIONS.TEMPLATE_DEFN_ID = HRA_TMPL_DEFNS_B.TEMPLATE_DEFN_ID AND HRA_TMPL_SECTIONS.BUSINESS_GROUP_ID = HRA_TMPL_DEFNS_B.BUSINESS_GROUP_ID AND SECTION_TYPE_CODE = 'GOAL') THEN (SELECT ROUNDING_RULE_CODE FROM HRA_TMPL_SECTIONS WHERE HRA_TMPL_SECTIONS.TEMPLATE_DEFN_ID = HRA_TMPL_DEFNS_B.TEMPLATE_DEFN_ID AND HRA_TMPL_SECTIONS.BUSINESS_GROUP_ID = HRA_TMPL_DEFNS_B.BUSINESS_GROUP_ID AND SECTION_TYPE_CODE = 'GOAL') ELSE NULL END ROUNDING_RULE_CODE, CASE WHEN EXISTS (SELECT 1 FROM HRA_TMPL_SECTIONS WHERE HRA_TMPL_SECTIONS.TEMPLATE_DEFN_ID = HRA_TMPL_DEFNS_B.TEMPLATE_DEFN_ID AND HRA_TMPL_SECTIONS.BUSINESS_GROUP_ID = HRA_TMPL_DEFNS_B.BUSINESS_GROUP_ID AND SECTION_TYPE_CODE = 'OS') THEN (SELECT DECIMAL_PLACES FROM HRA_TMPL_SECTIONS WHERE HRA_TMPL_SECTIONS.TEMPLATE_DEFN_ID = HRA_TMPL_DEFNS_B.TEMPLATE_DEFN_ID AND HRA_TMPL_SECTIONS.BUSINESS_GROUP_ID = HRA_TMPL_DEFNS_B.BUSINESS_GROUP_ID AND SECTION_TYPE_CODE = 'OS') WHEN EXISTS (SELECT 1 FROM HRA_TMPL_SECTIONS WHERE HRA_TMPL_SECTIONS.TEMPLATE_DEFN_ID = HRA_TMPL_DEFNS_B.TEMPLATE_DEFN_ID AND HRA_TMPL_SECTIONS.BUSINESS_GROUP_ID = HRA_TMPL_DEFNS_B.BUSINESS_GROUP_ID AND SECTION_TYPE_CODE = 'REG') THEN (SELECT DECIMAL_PLACES FROM HRA_TMPL_SECTIONS WHERE HRA_TMPL_SECTIONS.TEMPLATE_DEFN_ID = HRA_TMPL_DEFNS_B.TEMPLATE_DEFN_ID AND HRA_TMPL_SECTIONS.BUSINESS_GROUP_ID = HRA_TMPL_DEFNS_B.BUSINESS_GROUP_ID AND SECTION_TYPE_CODE = 'REG') WHEN EXISTS (SELECT 1 FROM HRA_TMPL_SECTIONS WHERE HRA_TMPL_SECTIONS.TEMPLATE_DEFN_ID = HRA_TMPL_DEFNS_B.TEMPLATE_DEFN_ID AND HRA_TMPL_SECTIONS.BUSINESS_GROUP_ID = HRA_TMPL_DEFNS_B.BUSINESS_GROUP_ID AND SECTION_TYPE_CODE = 'GOAL') THEN (SELECT DECIMAL_PLACES FROM HRA_TMPL_SECTIONS WHERE HRA_TMPL_SECTIONS.TEMPLATE_DEFN_ID = HRA_TMPL_DEFNS_B.TEMPLATE_DEFN_ID AND HRA_TMPL_SECTIONS.BUSINESS_GROUP_ID = HRA_TMPL_DEFNS_B.BUSINESS_GROUP_ID AND SECTION_TYPE_CODE = 'GOAL') ELSE NULL END DECIMAL_PLACES, CASE WHEN EXISTS (SELECT 1 FROM HRA_TMPL_SECTIONS WHERE HRA_TMPL_SECTIONS.TEMPLATE_DEFN_ID = HRA_TMPL_DEFNS_B.TEMPLATE_DEFN_ID AND HRA_TMPL_SECTIONS.BUSINESS_GROUP_ID = HRA_TMPL_DEFNS_B.BUSINESS_GROUP_ID AND SECTION_TYPE_CODE = 'OS') THEN (SELECT MAPPING_METHOD_CODE FROM HRA_TMPL_SECTIONS WHERE HRA_TMPL_SECTIONS.TEMPLATE_DEFN_ID = HRA_TMPL_DEFNS_B.TEMPLATE_DEFN_ID AND HRA_TMPL_SECTIONS.BUSINESS_GROUP_ID = HRA_TMPL_DEFNS_B.BUSINESS_GROUP_ID AND SECTION_TYPE_CODE = 'OS') WHEN EXISTS (SELECT 1 FROM HRA_TMPL_SECTIONS WHERE HRA_TMPL_SECTIONS.TEMPLATE_DEFN_ID = HRA_TMPL_DEFNS_B.TEMPLATE_DEFN_ID AND HRA_TMPL_SECTIONS.BUSINESS_GROUP_ID = HRA_TMPL_DEFNS_B.BUSINESS_GROUP_ID AND SECTION_TYPE_CODE = 'REG') THEN (SELECT MAPPING_METHOD_CODE FROM HRA_TMPL_SECTIONS WHERE HRA_TMPL_SECTIONS.TEMPLATE_DEFN_ID = HRA_TMPL_DEFNS_B.TEMPLATE_DEFN_ID AND HRA_TMPL_SECTIONS.BUSINESS_GROUP_ID = HRA_TMPL_DEFNS_B.BUSINESS_GROUP_ID AND SECTION_TYPE_CODE = 'REG') WHEN EXISTS (SELECT 1 FROM HRA_TMPL_SECTIONS WHERE HRA_TMPL_SECTIONS.TEMPLATE_DEFN_ID = HRA_TMPL_DEFNS_B.TEMPLATE_DEFN_ID AND HRA_TMPL_SECTIONS.BUSINESS_GROUP_ID = HRA_TMPL_DEFNS_B.BUSINESS_GROUP_ID AND SECTION_TYPE_CODE = 'GOAL') THEN (SELECT MAPPING_METHOD_CODE FROM HRA_TMPL_SECTIONS WHERE HRA_TMPL_SECTIONS.TEMPLATE_DEFN_ID = HRA_TMPL_DEFNS_B.TEMPLATE_DEFN_ID AND HRA_TMPL_SECTIONS.BUSINESS_GROUP_ID = HRA_TMPL_DEFNS_B.BUSINESS_GROUP_ID AND SECTION_TYPE_CODE = 'GOAL') ELSE NULL END MAPPING_METHOD_CODE, HRA_TMPL_DEFNS_B.SHOW_PARTICIPANT_NAMES SHOW_PARTICIPANT_NAMES, HRA_TMPL_DEFNS_B.SELECT_MGR_ALLOWED_FLAG SELECT_MGR_ALLOWED_FLAG, HRA_TMPL_DEFNS_B.STAR_RATING_ENABLED_FLAG STAR_RATING_ENABLED_FLAG, HRA_TMPL_DEFNS_B.SET_ROLE_MINIMUMS_FLAG SET_ROLE_MINIMUMS_FLAG, HRA_TMPL_DEFNS_B.TOTAL_MIN_PARTICIPANTS TOTAL_MIN_PARTICIPANTS, HRA_TMPL_DEFNS_B.USE_WRK_CONNECTIONS_FLAG USE_WRK_CONNECTIONS_FLAG, HRA_TMPL_DEFNS_B.WRK_SEE_MGR_PCPN_FLAG WRK_SEE_MGR_PCPN_FLAG, HRA_TMPL_DEFNS_B.PCPN_FEEDBACK_REQ_FLAG PCPN_FEEDBACK_REQ_FLAG, HRA_TMPL_DEFNS_B.PCPN_DECLINE_OPTION_FLAG PCPN_DECLINE_OPTION_FLAG, HRA_TMPL_DEFNS_B.AUTO_POPULATE_MM_FLAG AUTO_POPULATE_MM_FLAG, HRA_TMPL_DEFNS_B.SEND_REQUEST_TO_MM_FLAG SEND_REQUEST_TO_MM_FLAG, HRA_TMPL_DEFNS_B.DEFAULT_MATRIX_PCPN_ROLE_ID DEFAULT_MATRIX_PCPN_ROLE_ID, HRA_TMPL_DEFNS_B.ATTRIBUTE_CATEGORY ATTRIBUTE_CATEGORY, HRA_TMPL_DEFNS_B.ATTRIBUTE1 ATTRIBUTE1, HRA_TMPL_DEFNS_B.ATTRIBUTE2 ATTRIBUTE2, HRA_TMPL_DEFNS_B.ATTRIBUTE3 ATTRIBUTE3, HRA_TMPL_DEFNS_B.ATTRIBUTE4 ATTRIBUTE4, HRA_TMPL_DEFNS_B.ATTRIBUTE5 ATTRIBUTE5, HRA_TMPL_DEFNS_B.ATTRIBUTE6 ATTRIBUTE6, HRA_TMPL_DEFNS_B.ATTRIBUTE7 ATTRIBUTE7, HRA_TMPL_DEFNS_B.ATTRIBUTE8 ATTRIBUTE8, HRA_TMPL_DEFNS_B.ATTRIBUTE9 ATTRIBUTE9, HRA_TMPL_DEFNS_B.ATTRIBUTE10 ATTRIBUTE10, HRA_TMPL_DEFNS_B.ATTRIBUTE11 ATTRIBUTE11, HRA_TMPL_DEFNS_B.ATTRIBUTE12 ATTRIBUTE12, HRA_TMPL_DEFNS_B.ATTRIBUTE13 ATTRIBUTE13, HRA_TMPL_DEFNS_B.ATTRIBUTE14 ATTRIBUTE14, HRA_TMPL_DEFNS_B.ATTRIBUTE15 ATTRIBUTE15, HRA_TMPL_DEFNS_B.ATTRIBUTE16 ATTRIBUTE16, HRA_TMPL_DEFNS_B.ATTRIBUTE17 ATTRIBUTE17, HRA_TMPL_DEFNS_B.ATTRIBUTE18 ATTRIBUTE18, HRA_TMPL_DEFNS_B.ATTRIBUTE19 ATTRIBUTE19, HRA_TMPL_DEFNS_B.ATTRIBUTE20 ATTRIBUTE20, HRA_TMPL_DEFNS_B.ATTRIBUTE21 ATTRIBUTE21, HRA_TMPL_DEFNS_B.ATTRIBUTE22 ATTRIBUTE22, HRA_TMPL_DEFNS_B.ATTRIBUTE23 ATTRIBUTE23, HRA_TMPL_DEFNS_B.ATTRIBUTE24 ATTRIBUTE24, HRA_TMPL_DEFNS_B.ATTRIBUTE25 ATTRIBUTE25, HRA_TMPL_DEFNS_B.ATTRIBUTE26 ATTRIBUTE26, HRA_TMPL_DEFNS_B.ATTRIBUTE27 ATTRIBUTE27, HRA_TMPL_DEFNS_B.ATTRIBUTE28 ATTRIBUTE28, HRA_TMPL_DEFNS_B.ATTRIBUTE29 ATTRIBUTE29, HRA_TMPL_DEFNS_B.ATTRIBUTE30 ATTRIBUTE30, HRA_TMPL_DEFNS_B.ATTRIBUTE_NUMBER1 ATTRIBUTE_NUMBER1, HRA_TMPL_DEFNS_B.ATTRIBUTE_NUMBER2 ATTRIBUTE_NUMBER2, HRA_TMPL_DEFNS_B.ATTRIBUTE_NUMBER3 ATTRIBUTE_NUMBER3, HRA_TMPL_DEFNS_B.ATTRIBUTE_NUMBER4 ATTRIBUTE_NUMBER4, HRA_TMPL_DEFNS_B.ATTRIBUTE_NUMBER5 ATTRIBUTE_NUMBER5, HRA_TMPL_DEFNS_B.ATTRIBUTE_NUMBER6 ATTRIBUTE_NUMBER6, HRA_TMPL_DEFNS_B.ATTRIBUTE_NUMBER7 ATTRIBUTE_NUMBER7, HRA_TMPL_DEFNS_B.ATTRIBUTE_NUMBER8 ATTRIBUTE_NUMBER8, HRA_TMPL_DEFNS_B.ATTRIBUTE_NUMBER9 ATTRIBUTE_NUMBER9, HRA_TMPL_DEFNS_B.ATTRIBUTE_NUMBER10 ATTRIBUTE_NUMBER10, HRA_TMPL_DEFNS_B.ATTRIBUTE_NUMBER11 ATTRIBUTE_NUMBER11, HRA_TMPL_DEFNS_B.ATTRIBUTE_NUMBER12 ATTRIBUTE_NUMBER12, HRA_TMPL_DEFNS_B.ATTRIBUTE_NUMBER13 ATTRIBUTE_NUMBER13, HRA_TMPL_DEFNS_B.ATTRIBUTE_NUMBER14 ATTRIBUTE_NUMBER14, HRA_TMPL_DEFNS_B.ATTRIBUTE_NUMBER15 ATTRIBUTE_NUMBER15, HRA_TMPL_DEFNS_B.ATTRIBUTE_NUMBER16 ATTRIBUTE_NUMBER16, HRA_TMPL_DEFNS_B.ATTRIBUTE_NUMBER17 ATTRIBUTE_NUMBER17, HRA_TMPL_DEFNS_B.ATTRIBUTE_NUMBER18 ATTRIBUTE_NUMBER18, HRA_TMPL_DEFNS_B.ATTRIBUTE_NUMBER19 ATTRIBUTE_NUMBER19, HRA_TMPL_DEFNS_B.ATTRIBUTE_NUMBER20 ATTRIBUTE_NUMBER20, HRA_TMPL_DEFNS_B.ATTRIBUTE_DATE1 ATTRIBUTE_DATE1, HRA_TMPL_DEFNS_B.ATTRIBUTE_DATE2 ATTRIBUTE_DATE2, HRA_TMPL_DEFNS_B.ATTRIBUTE_DATE3 ATTRIBUTE_DATE3, HRA_TMPL_DEFNS_B.ATTRIBUTE_DATE4 ATTRIBUTE_DATE4, HRA_TMPL_DEFNS_B.ATTRIBUTE_DATE5 ATTRIBUTE_DATE5, HRA_TMPL_DEFNS_B.ATTRIBUTE_DATE6 ATTRIBUTE_DATE6, HRA_TMPL_DEFNS_B.ATTRIBUTE_DATE7 ATTRIBUTE_DATE7, HRA_TMPL_DEFNS_B.ATTRIBUTE_DATE8 ATTRIBUTE_DATE8, HRA_TMPL_DEFNS_B.ATTRIBUTE_DATE9 ATTRIBUTE_DATE9, HRA_TMPL_DEFNS_B.ATTRIBUTE_DATE10 ATTRIBUTE_DATE10, HRA_TMPL_DEFNS_B.ATTRIBUTE_DATE11 ATTRIBUTE_DATE11, HRA_TMPL_DEFNS_B.ATTRIBUTE_DATE12 ATTRIBUTE_DATE12, HRA_TMPL_DEFNS_B.ATTRIBUTE_DATE13 ATTRIBUTE_DATE13, HRA_TMPL_DEFNS_B.ATTRIBUTE_DATE14 ATTRIBUTE_DATE14, HRA_TMPL_DEFNS_B.ATTRIBUTE_DATE15 ATTRIBUTE_DATE15, HRA_TMPL_DEFNS_B.OBJECT_VERSION_NUMBER OBJECT_VERSION_NUMBER, HRA_TMPL_DEFNS_B.CREATED_BY CREATED_BY, HRA_TMPL_DEFNS_B.CREATION_DATE CREATION_DATE, HRA_TMPL_DEFNS_B.LAST_UPDATED_BY LAST_UPDATED_BY, HRA_TMPL_DEFNS_B.LAST_UPDATE_DATE LAST_UPDATE_DATE, HRA_TMPL_DEFNS_B.LAST_UPDATE_LOGIN LAST_UPDATE_LOGIN, HRA_TMPL_DEFNS_B.DIGITAL_SIGNATURE_FLAG DIGITAL_SIGNATURE_FLAG, HRA_TMPL_DEFNS_B.MODULE_ID MODULE_ID, HRA_TMPL_DEFNS_B.KUDOS_REGION_FLAG KUDOS_REGION_FLAG, HRA_TMPL_DEFNS_B.SHOW_WKR_CALC_RATING_FLAG SHOW_WKR_CALC_RATING_FLAG, HRA_TMPL_DEFNS_B.SHOW_MGR_CALC_RATING_FLAG SHOW_MGR_CALC_RATING_FLAG, HRA_TMPL_DEFNS_B.SHOW_MM_CALC_RATING_FLAG SHOW_MM_CALC_RATING_FLAG, HRA_TMPL_DEFNS_B.SHOW_PCPN_CALC_RATING_FLAG SHOW_PCPN_CALC_RATING_FLAG FROM HRA_TMPL_DEFNS_B",
  "_parsed_at": "2026-06-09T18:19:39"
}